DPAPI/__init__.py
DPAPI/probe.py
DPAPI/Core/registry.py
DPAPI/Core/crypto.py
DPAPI/Core/masterkey.py
DPAPI/Core/credhist.py
DPAPI/Core/blob.py
DPAPI/Core/__init__.py
DPAPI/Core/eater.py
DPAPI/Probes/credstore.py
DPAPI/Probes/safari.py
DPAPI/Probes/chrome.py
DPAPI/Probes/icloud.py
DPAPI/Probes/skype.py
DPAPI/Probes/IE7.py
DPAPI/Probes/certificate.py
DPAPI/Probes/wifi.py
DPAPI/Probes/__init__.py
DPAPI/Probes/gtalk.py
DPAPI/Probes/dropbox.py
DPAPI/Probes/RDP.py
dpapick-0.3.data/scripts/dpapidec
dpapick-0.3.dist-info/RECORD
dpapick-0.3.dist-info/METADATA
dpapick-0.3.dist-info/top_level.txt
dpapick-0.3.dist-info/DESCRIPTION.rst
dpapick-0.3.dist-info/WHEEL
dpapick-0.3.dist-info/dependency_links.txt
dpapick-0.3.dist-info/metadata.json
