Metadata-Version: 2.0
Name: dpapick
Version: 0.3
Summary: DPAPI decryption toolkit
Home-page: http://www.dpapick.com
Author: Jean-Michel PICOD
Author-email: jmichel.p@gmail.com
License: GPLv3
Download-URL: https://bitbucket.org/jmichel/dpapick/downloads
Platform: UNKNOWN
Classifier: Development Status :: 4 - Beta
Classifier: Environment :: Console
Classifier: Intended Audience :: Developers
Classifier: Intended Audience :: Information Technology
Classifier: License :: OSI Approved :: GNU General Public License v3 (GPLv3)
Classifier: Natural Language :: English
Classifier: Operating System :: OS Independent
Classifier: Programming Language :: Python :: 2.7
Classifier: Topic :: Security :: Cryptography
Classifier: Topic :: Software Development :: Libraries :: Python Modules
Classifier: Topic :: System :: Recovery Tools
Requires-Dist: M2Crypto (>=0.21.1)
Requires-Dist: python-registry (>=1.0.4)
Requires-Dist: pyasn1 (>=0.1.7)
Requires-Dist: CFPropertyList
